speciesot/__init__.py
speciesot/speciesot.py
speciesot-0.2.7.dist-info/LICENSE
speciesot-0.2.7.dist-info/METADATA
speciesot-0.2.7.dist-info/WHEEL
speciesot-0.2.7.dist-info/RECORD
