Metadata-Version: 2.1
Name: speciesot
Version: 0.2.7
Summary: Geometric inference of cross-species transcriptome correspondence using Gromov–Wasserstein optimal transport.
Author: Yuya Tokuta
Requires-Python: ==3.12.7
Classifier: Programming Language :: Python :: 3
Requires-Dist: anndata (==0.11.4)
Requires-Dist: jax (>=0.4.26,<0.4.27) ; sys_platform == "darwin"
Requires-Dist: jax-metal (==0.1.0) ; sys_platform == "darwin"
Requires-Dist: jax[cuda12] (>=0.4.26,<0.4.27) ; sys_platform == "linux"
Requires-Dist: jaxlib (>=0.4.26,<0.4.27)
Requires-Dist: jupyter-black (==0.4.0)
Requires-Dist: nbformat (==5.10.4)
Requires-Dist: ott-jax (==0.4.9)
Requires-Dist: plotly (==5.24.1)
Requires-Dist: polars (==1.15.0)
Requires-Dist: pyarrow (==18.0.0)
Requires-Dist: scanpy (==1.11.5)
Requires-Dist: screcode (==1.0.0)
